mongo_tooling_metrics/__init__.py
mongo_tooling_metrics/base_hook.py
mongo_tooling_metrics/base_metrics.py
mongo_tooling_metrics/client.py
mongo_tooling_metrics/errors.py
mongo_tooling_metrics/lib/hooks.py
mongo_tooling_metrics/lib/sub_metrics.py
mongo_tooling_metrics/lib/top_level_metrics.py
mongo_tooling_metrics/lib/utils.py
mongo_tooling_metrics/registry.py
mongo_tooling_metrics-1.0.7.dist-info/WHEEL
mongo_tooling_metrics-1.0.7.dist-info/METADATA
mongo_tooling_metrics-1.0.7.dist-info/RECORD
