Metadata-Version: 2.1
Name: mongo-tooling-metrics
Version: 1.0.7
Summary: A slim library which leverages Pydantic to reliably collect type enforced metrics and store them to MongoDB.
Author: Tausif Rahman
Author-email: tausif.rahman@mongodb.com
Requires-Python: >=3.7,<4.0
Classifier: Programming Language :: Python :: 3
Classifier: Programming Language :: Python :: 3.7
Classifier: Programming Language :: Python :: 3.8
Classifier: Programming Language :: Python :: 3.9
Classifier: Programming Language :: Python :: 3.10
Classifier: Programming Language :: Python :: 3.11
Requires-Dist: distro (>=1.5.0,<2.0.0)
Requires-Dist: gitpython (>=3.1.29,<4.0.0)
Requires-Dist: pydantic (>=1.8.2,<2.0.0)
Requires-Dist: pymongo (>=4.3.3,<5.0.0)
Requires-Dist: setuptools (>=58.1.0,<59.0.0)
